gradient_reversal/__init__.py
gradient_reversal/gradient_reversal.py
torch_gradient_reversal-1.0.0.dist-info/licenses/LICENSE
torch_gradient_reversal-1.0.0.dist-info/METADATA
torch_gradient_reversal-1.0.0.dist-info/WHEEL
torch_gradient_reversal-1.0.0.dist-info/top_level.txt
torch_gradient_reversal-1.0.0.dist-info/RECORD
