Metadata-Version: 2.4
Name: torch-gradient-reversal
Version: 1.0.0
Summary: Gradient Reversal Layer implemented with torch.library
Author: Andrew Bistras
License-Expression: MIT
Project-URL: Source, https://github.com/andrewbistras/torch-gradient-reversal
Requires-Python: >=3.9
License-File: LICENSE
Requires-Dist: torch>=2.7
Dynamic: license-file
